csv_parse/__init__.py
csv_parse/reader.py
csvparse-0.0.3.dist-info/DESCRIPTION.rst
csvparse-0.0.3.dist-info/METADATA
csvparse-0.0.3.dist-info/RECORD
csvparse-0.0.3.dist-info/WHEEL
csvparse-0.0.3.dist-info/metadata.json
csvparse-0.0.3.dist-info/top_level.txt
