Metadata-Version: 2.0
Name: csvparse
Version: 0.0.3
Summary: A simple state-machine based CSV parser.
Home-page: https://github.com/andrewgross/csv_read
Author: Andrew Gross
Author-email: andrew.w.gross@gmail.com
License: UNKNOWN
Platform: UNKNOWN
